discord/__init__.py
discord/__main__.py
discord/abc.py
discord/activity.py
discord/appinfo.py
discord/asset.py
discord/audit_logs.py
discord/backoff.py
discord/channel.py
discord/client.py
discord/colour.py
discord/components.py
discord/context_managers.py
discord/embeds.py
discord/emoji.py
discord/enums.py
discord/errors.py
discord/file.py
discord/flags.py
discord/gateway.py
discord/guild.py
discord/http.py
discord/integrations.py
discord/interactions.py
discord/invite.py
discord/iterators.py
discord/member.py
discord/mentions.py
discord/message.py
discord/mixins.py
discord/object.py
discord/oggparse.py
discord/opus.py
discord/partial_emoji.py
discord/permissions.py
discord/player.py
discord/py.typed
discord/raw_models.py
discord/reaction.py
discord/role.py
discord/shard.py
discord/stage_instance.py
discord/state.py
discord/sticker.py
discord/team.py
discord/template.py
discord/threads.py
discord/user.py
discord/utils.py
discord/voice_client.py
discord/widget.py
discord/zarena.py
discord/bin/libopus-0.x64.dll
discord/bin/libopus-0.x86.dll
discord/ext/commands/__init__.py
discord/ext/commands/_types.py
discord/ext/commands/bot.py
discord/ext/commands/cog.py
discord/ext/commands/context.py
discord/ext/commands/converter.py
discord/ext/commands/cooldowns.py
discord/ext/commands/core.py
discord/ext/commands/errors.py
discord/ext/commands/flags.py
discord/ext/commands/help.py
discord/ext/commands/view.py
discord/ext/tasks/__init__.py
discord/types/__init__.py
discord/types/activity.py
discord/types/appinfo.py
discord/types/audit_log.py
discord/types/channel.py
discord/types/components.py
discord/types/embed.py
discord/types/emoji.py
discord/types/gateway.py
discord/types/guild.py
discord/types/integration.py
discord/types/interactions.py
discord/types/invite.py
discord/types/member.py
discord/types/message.py
discord/types/raw_models.py
discord/types/role.py
discord/types/snowflake.py
discord/types/sticker.py
discord/types/team.py
discord/types/template.py
zarenacord-2.0.0.dist-info/LICENSE
zarenacord-2.0.0.dist-info/METADATA
zarenacord-2.0.0.dist-info/WHEEL
zarenacord-2.0.0.dist-info/top_level.txt
zarenacord-2.0.0.dist-info/RECORD
